AlexFireBot/__init__.py
AlexFireBot/clients.py
AlexFireBot/config.py
AlexFireBot/events.py
AlexFireBot-0.0.dist-info/LICENSE
AlexFireBot-0.0.dist-info/METADATA
AlexFireBot-0.0.dist-info/WHEEL
AlexFireBot-0.0.dist-info/top_level.txt
AlexFireBot-0.0.dist-info/RECORD
